client/__init__.py
client/client.py
client/client/__init__.py
client/client/add_contact.py
client/client/client_database.py
client/client/client_window.py
client/client/delete_contact.py
client/client/main_window.py
client/client/start_dialog.py
client/client/transport.py
client/logs/__init__.py
client/logs/client_log_config.py
client/logs/server_log_config.py
client/modules/__init__.py
client/modules/decos.py
client/modules/descriptors.py
client/modules/functions.py
client/modules/metaclasses.py
client/modules/variables.py
client/unit_tests/__init__.py
mess_client_project-1.0.0.dist-info/METADATA
mess_client_project-1.0.0.dist-info/WHEEL
mess_client_project-1.0.0.dist-info/top_level.txt
mess_client_project-1.0.0.dist-info/RECORD
